{
  "id": "98dcea1c-16e9-4652-b79a-3682127c7bd5",
  "prevId": "a272c7b2-d543-4a88-ab79-ecd061a4eaec",
  "version": "7",
  "dialect": "postgresql",
  "tables": {
    "public.availify_images": {
      "name": "availify_images",
      "schema": "",
      "columns": {
        "id": {
          "name": "id",
          "type": "uuid",
          "primaryKey": true,
          "notNull": true,
          "default": "gen_random_uuid()"
        },
        "name": {
          "name": "name",
          "type": "varchar(256)",
          "primaryKey": false,
          "notNull": true
        },
        "url": {
          "name": "url",
          "type": "varchar(512)",
          "primaryKey": false,
          "notNull": true
        }
      },
      "indexes": {
        "name_idx": {
          "name": "name_idx",
          "columns": [
            {
              "expression": "name",
              "isExpression": false,
              "asc": true,
              "nulls": "last"
            }
          ],
          "isUnique": false,
          "concurrently": false,
          "method": "btree",
          "with": {}
        }
      },
      "foreignKeys": {},
      "compositePrimaryKeys": {},
      "uniqueConstraints": {}
    },
    "public.availify_products": {
      "name": "availify_products",
      "schema": "",
      "columns": {
        "id": {
          "name": "id",
          "type": "uuid",
          "primaryKey": true,
          "notNull": true,
          "default": "gen_random_uuid()"
        },
        "title": {
          "name": "title",
          "type": "varchar(256)",
          "primaryKey": false,
          "notNull": true
        },
        "description": {
          "name": "description",
          "type": "text",
          "primaryKey": false,
          "notNull": true
        },
        "price": {
          "name": "price",
          "type": "numeric(10, 2)",
          "primaryKey": false,
          "notNull": true
        },
        "image_url": {
          "name": "image_url",
          "type": "varchar(512)",
          "primaryKey": false,
          "notNull": false
        },
        "created_at": {
          "name": "created_at",
          "type": "timestamp with time zone",
          "primaryKey": false,
          "notNull": true,
          "default": "CURRENT_TIMESTAMP"
        },
        "updated_at": {
          "name": "updated_at",
          "type": "timestamp with time zone",
          "primaryKey": false,
          "notNull": false
        }
      },
      "indexes": {
        "title_idx": {
          "name": "title_idx",
          "columns": [
            {
              "expression": "title",
              "isExpression": false,
              "asc": true,
              "nulls": "last"
            }
          ],
          "isUnique": false,
          "concurrently": false,
          "method": "btree",
          "with": {}
        }
      },
      "foreignKeys": {},
      "compositePrimaryKeys": {},
      "uniqueConstraints": {}
    },
    "public.availify_weekly_menu": {
      "name": "availify_weekly_menu",
      "schema": "",
      "columns": {
        "id": {
          "name": "id",
          "type": "uuid",
          "primaryKey": true,
          "notNull": true,
          "default": "gen_random_uuid()"
        },
        "product_id": {
          "name": "product_id",
          "type": "uuid",
          "primaryKey": false,
          "notNull": true
        },
        "day_of_week": {
          "name": "day_of_week",
          "type": "varchar(10)",
          "primaryKey": false,
          "notNull": true
        }
      },
      "indexes": {
        "product_idx": {
          "name": "product_idx",
          "columns": [
            {
              "expression": "product_id",
              "isExpression": false,
              "asc": true,
              "nulls": "last"
            }
          ],
          "isUnique": false,
          "concurrently": false,
          "method": "btree",
          "with": {}
        }
      },
      "foreignKeys": {},
      "compositePrimaryKeys": {},
      "uniqueConstraints": {}
    }
  },
  "enums": {},
  "schemas": {},
  "sequences": {},
  "_meta": {
    "columns": {},
    "schemas": {},
    "tables": {}
  }
}